navinfo_tool/__init__.py
navinfo_tool/end_words.py
navinfo_tool/rule_error_identification.py
navinfo_tool/rule_error_identification1009.py
navinfo_tool/same_stroke.py
navinfo_tool/utils.py
navinfo_tool-0.1.8.dist-info/METADATA
navinfo_tool-0.1.8.dist-info/WHEEL
navinfo_tool-0.1.8.dist-info/top_level.txt
navinfo_tool-0.1.8.dist-info/RECORD
