Metadata-Version: 2.1
Name: navinfo-tool
Version: 0.1.8
Summary: utils for nlp
Author: navinfo_nlp
Author-email: navinfo_nlp@163.com
License: Apache License 2.0
Requires-Dist: xlrd (==1.2.0)
Requires-Dist: jieba
Requires-Dist: xlwt
Requires-Dist: xlutils
Requires-Dist: matplotlib
Requires-Dist: scikit-learn
Requires-Dist: pandas
Requires-Dist: fairies
Requires-Dist: configparser
Requires-Dist: xpinyin (==0.7.6)
Requires-Dist: xlsxwriter (==3.0.1)
Requires-Dist: tqdm
